{"blog": [], "source": "AP", "document_type": "article", "word_count": "853", "lead_paragraph": "Sean Henry, the president of Tennessee's NHL team, is stunned he even has to explain why he hopes state legislators will snub bills similar to North Carolina's transgender bathroom law, which has consumed that state for months and scared off businesses and sporting events.", "web_url": "http://www.nytimes.com/aponline/2017/01/01/us/ap-us-lgbt-bills-backlash.html", "print_page": null, "section_name": "U.S.", "abstract": null, "keywords": [], "_id": "5869134995d0e039260788b5", "snippet": "Sean Henry, the president of Tennessee's NHL team, is stunned he even has to explain why he hopes state legislators will snub bills similar to North Carolina's transgender bathroom law, which has consumed that state for months and scared off busin...", "news_desk": null, "slideshow_credits": null, "byline": {"organization": "THE ASSOCIATED PRESS", "person": [], "original": "By THE ASSOCIATED PRESS"}, "multimedia": [], "headline": {"main": "In Red States, Businesses Gearing Up to Fight Bathroom Bills", "print_headline": "In Red States, Businesses Gearing Up to Fight Bathroom Bills"}, "type_of_material": "News", "pub_date": "2017-01-01T14:33:36+0000", "subsection_name": null}