{"_id": "58462dc795d0e03926074482", "section_name": "Sports", "keywords": [], "byline": {"person": [], "original": "By THE ASSOCIATED PRESS", "organization": "THE ASSOCIATED PRESS"}, "word_count": "752", "web_url": "http://www.nytimes.com/aponline/2016/12/05/sports/ncaabasketball/ap-bkc-thunder-hawks.html", "lead_paragraph": "At first, Russell Westbrook couldn't get the shots to fall. No problem. He crashed the boards and kept looking for his teammates.", "headline": {"main": "Westbrook's Triple-Double Leads Thunder Past Hawks, 102-99", "print_headline": "Westbrook's Triple-Double Leads Thunder Past Hawks, 102-99"}, "document_type": "article", "blog": [], "print_page": null, "subsection_name": "College Basketball", "slideshow_credits": null, "abstract": null, "source": "AP", "news_desk": null, "type_of_material": "News", "pub_date": "2016-12-06T03:17:21+0000", "snippet": "At first, Russell Westbrook couldn't get the shots to fall. No problem. He crashed the boards and kept looking for his teammates....", "multimedia": []}