{"snippet": "Two-time major champion Stan Wawrinka pulled out of the Olympics on Tuesday because of injury, leaving the Rio Games without half of the men ranked in the ATP's top 10....", "source": "AP", "byline": {"organization": "THE ASSOCIATED PRESS", "person": [], "original": "By THE ASSOCIATED PRESS"}, "word_count": "217", "type_of_material": "News", "keywords": [], "blog": [], "print_page": null, "multimedia": [], "_id": "57a0d2b138f0d8762aab680f", "document_type": "article", "slideshow_credits": null, "lead_paragraph": "Two-time major champion Stan Wawrinka pulled out of the Olympics on Tuesday because of injury, leaving the Rio Games without half of the men ranked in the ATP's top 10.", "web_url": "http://www.nytimes.com/aponline/2016/08/02/sports/olympics/ap-oly-ten-wawrinka-withdraws.html", "abstract": null, "subsection_name": "Olympics", "headline": {"print_headline": "Switzerland's Stan Wawrinka Pulls Out of Rio Olympics", "main": "Switzerland's Stan Wawrinka Pulls Out of Rio Olympics"}, "pub_date": "2016-08-02T12:59:51Z", "section_name": "Sports", "news_desk": "None"}