{"blog": [], "source": "Reuters", "document_type": "article", "word_count": "284", "lead_paragraph": "Sam Querrey said this year's Wimbledon had been a triumph for the United States after the nation's best showing at the championships for 12 years.", "web_url": "http://www.nytimes.com/reuters/2016/07/06/sports/tennis/06reuters-tennis-wimbledon-querrey.html", "print_page": null, "section_name": "Sports", "abstract": null, "keywords": [], "_id": "577d393038f0d85bf991f982", "snippet": "Sam Querrey said this year's Wimbledon had been a triumph for the United States after the nation's best showing at the championships for 12 years....", "news_desk": "None", "slideshow_credits": null, "byline": {"organization": "REUTERS", "person": [], "original": "By REUTERS"}, "multimedia": [], "headline": {"main": "Querrey Hails American Success at Wimbledon", "print_headline": "Querrey Hails American Success at Wimbledon"}, "type_of_material": "News", "pub_date": "2016-07-06T12:56:25Z", "subsection_name": "Tennis"}