[{"rank_last_week": 2, "amazon_product_url": "http://www.amazon.com/Magnus-Chase-Gods-Asgard-Hammer/dp/1423160924?tag=thenewyorktim-20", "dagger": 0, "list_name": "Childrens Middle Grade E-Book", "published_date": "2017-01-29", "isbns": [{"isbn10": "1423160924", "isbn13": "9781423160922"}, {"isbn10": "1368000312", "isbn13": "9781368000314"}, {"isbn10": "1484758455", "isbn13": "9781484758458"}], "book_details": [{"contributor": "by Rick Riordan", "primary_isbn10": "None", "primary_isbn13": "9781484758595", "description": "Magnus Chase and his friends must find Thor\u2019s signature accessory.", "price": 0, "author": "Rick Riordan", "contributor_note": "", "publisher": "Disney-Hyperion", "title": "THE HAMMER OF THOR", "age_group": ""}], "bestsellers_date": "2017-01-14", "display_name": "Children\u2019s Middle Grade E-Book", "rank": 1, "asterisk": 0, "reviews": [{"article_chapter_link": "", "sunday_review_link": "", "first_chapter_link": "", "book_review_link": ""}], "weeks_on_list": 15}, {"rank_last_week": 5, "amazon_product_url": "http://www.amazon.com/Wonder-R-J-Palacio-ebook/dp/B0051ANPZQ?tag=thenewyorktim-20", "dagger": 0, "list_name": "Childrens Middle Grade E-Book", "published_date": "2017-01-29", "isbns": [{"isbn10": "0375869026", "isbn13": "9780375869020"}, {"isbn10": "037589988X", "isbn13": "9780375899881"}, {"isbn10": "0375969020", "isbn13": "9780375969027"}], "book_details": [{"contributor": "by R. J. Palacio", "primary_isbn10": "037589988X", "primary_isbn13": "9780375899881", "description": "A boy with a facial deformity starts school.", "price": 0, "author": "R J Palacio", "contributor_note": "", "publisher": "Knopf", "title": "WONDER", "age_group": ""}], "bestsellers_date": "2017-01-14", "display_name": "Children\u2019s Middle Grade E-Book", "rank": 2, "asterisk": 0, "reviews": [{"article_chapter_link": "", "sunday_review_link": "https://www.nytimes.com/2012/04/08/books/review/wonder-by-r-j-palacio.html", "first_chapter_link": "", "book_review_link": ""}], "weeks_on_list": 58}, {"rank_last_week": 3, "amazon_product_url": "http://www.amazon.com/The-Trials-Apollo-Book-Hidden/dp/148473274X?tag=thenewyorktim-20", "dagger": 0, "list_name": "Childrens Middle Grade E-Book", "published_date": "2017-01-29", "isbns": [{"isbn10": "148473274X", "isbn13": "9781484732748"}, {"isbn10": "1484786815", "isbn13": "9781484786819"}, {"isbn10": "1484746945", "isbn13": "9781484746943"}, {"isbn10": "1410489450", "isbn13": "9781410489456"}], "book_details": [{"contributor": "by Rick Riordan", "primary_isbn10": "None", "primary_isbn13": "9781484736678", "description": "Apollo, now a mortal teenager with acne, sets out to restore his tarnished reputation.", "price": 0, "author": "Rick Riordan", "contributor_note": "", "publisher": "Disney-Hyperion", "title": "THE HIDDEN ORACLE", "age_group": ""}], "bestsellers_date": "2017-01-14", "display_name": "Children\u2019s Middle Grade E-Book", "rank": 3, "asterisk": 0, "reviews": [{"article_chapter_link": "", "sunday_review_link": "", "first_chapter_link": "", "book_review_link": ""}], "weeks_on_list": 37}, {"rank_last_week": 0, "amazon_product_url": "http://www.amazon.com/Magnus-Chase-Gods-Asgard-Book-ebook/dp/B00O87NWBK?tag=thenewyorktim-20", "dagger": 0, "list_name": "Childrens Middle Grade E-Book", "published_date": "2017-01-29", "isbns": [{"isbn10": "1423160916", "isbn13": "9781423160915"}, {"isbn10": "1484719328", "isbn13": "9781484719329"}, {"isbn10": "1484718712", "isbn13": "9781484718711"}], "book_details": [{"contributor": "by Rick Riordan", "primary_isbn10": "1484719328", "primary_isbn13": "9781484719329", "description": "A teenager sets out to retrieve an ancient Norse sword.", "price": 0, "author": "Rick Riordan", "contributor_note": "", "publisher": "Disney-Hyperion", "title": "THE SWORD OF SUMMER", "age_group": ""}], "bestsellers_date": "2017-01-14", "display_name": "Children\u2019s Middle Grade E-Book", "rank": 4, "asterisk": 0, "reviews": [{"article_chapter_link": "", "sunday_review_link": "https://www.nytimes.com/2015/11/08/books/review/rick-riordans-magnus-chase-and-the-gods-of-asgard.html", "first_chapter_link": "", "book_review_link": ""}], "weeks_on_list": 55}, {"rank_last_week": 1, "amazon_product_url": "http://www.amazon.com/The-Finisher-Content-E-book-Edition-ebook/dp/B00EOALKXS?tag=thenewyorktim-20", "dagger": 0, "list_name": "Childrens Middle Grade E-Book", "published_date": "2017-01-29", "isbns": [], "book_details": [{"contributor": "by David Baldacci", "primary_isbn10": "None", "primary_isbn13": "9780545652360", "description": "Vega Jane looks into a friend's mysterious disappearance.", "price": 0, "author": "David Baldacci", "contributor_note": "", "publisher": "Scholastic", "title": "THE FINISHER", "age_group": ""}], "bestsellers_date": "2017-01-14", "display_name": "Children\u2019s Middle Grade E-Book", "rank": 5, "asterisk": 0, "reviews": [{"article_chapter_link": "", "sunday_review_link": "", "first_chapter_link": "", "book_review_link": ""}], "weeks_on_list": 18}]