[{"list_name": "Picture Books", "asterisk": 0, "published_date": "2017-03-12", "book_details": [{"primary_isbn13": "9780811877824", "contributor_note": "", "primary_isbn10": "0811877825", "description": "As the sun sets, hard-working trucks get ready for bed.", "contributor": "by Sherri Duskey Rinker and Tom Lichtenheld", "publisher": "Chronicle", "title": "GOODNIGHT, GOODNIGHT, CONSTRUCTION SITE", "author": "Sherri Duskey Rinker and Tom Lichtenheld", "age_group": "", "price": 0}], "weeks_on_list": 230, "bestsellers_date": "2017-02-25", "rank": 1, "display_name": "Children\u2019s Picture Books", "dagger": 0, "amazon_product_url": "http://www.amazon.com/Goodnight-Construction-Sherri-Duskey-Rinker/dp/0811877825?tag=thenewyorktim-20", "isbns": [{"isbn10": "0811877825", "isbn13": "9780811877824"}, {"isbn10": "1452152152", "isbn13": "9781452152158"}], "rank_last_week": 3, "reviews": [{"sunday_review_link": "", "article_chapter_link": "", "book_review_link": "https://www.nytimes.com/2011/05/18/books/review/childrens-books-bedtime-books-for-boys.html", "first_chapter_link": ""}]}, {"list_name": "Picture Books", "asterisk": 0, "published_date": "2017-03-12", "book_details": [{"primary_isbn13": "9781452152165", "contributor_note": "", "primary_isbn10": "1452152160", "description": "The vehicles do the heavy lifting and hard work needed to make a building rise.", "contributor": "by Sherri Duskey Rinker and Tom Lichtenheld", "publisher": "Chronicle", "title": "MIGHTY, MIGHTY CONSTRUCTION SITE", "author": "Sherri Duskey Rinker and Tom Lichtenheld", "age_group": "", "price": 0}], "weeks_on_list": 2, "bestsellers_date": "2017-02-25", "rank": 2, "display_name": "Children\u2019s Picture Books", "dagger": 0, "amazon_product_url": "https://www.amazon.com/Mighty-Construction-Sherri-Duskey-Rinker/dp/1452152160?tag=thenewyorktim-20", "isbns": [{"isbn10": "1452152160", "isbn13": "9781452152165"}], "rank_last_week": 1, "reviews": [{"sunday_review_link": "", "article_chapter_link": "", "book_review_link": "", "first_chapter_link": ""}]}, {"list_name": "Picture Books", "asterisk": 0, "published_date": "2017-03-12", "book_details": [{"primary_isbn13": "9780803736801", "contributor_note": "Illustrated by Daniel Salmieri", "primary_isbn10": "0803736800", "description": "What to serve your dragon-guests.", "contributor": "by Adam Rubin. Illustrated by Daniel Salmieri", "publisher": "Dial", "title": "DRAGONS LOVE TACOS", "author": "Adam Rubin", "age_group": "", "price": 0}], "weeks_on_list": 158, "bestsellers_date": "2017-02-25", "rank": 3, "display_name": "Children\u2019s Picture Books", "dagger": 0, "amazon_product_url": "http://www.amazon.com/Dragons-Love-Tacos-Adam-Rubin/dp/0803736800?tag=thenewyorktim-20", "isbns": [{"isbn10": "0803736800", "isbn13": "9780803736801"}], "rank_last_week": 5, "reviews": [{"sunday_review_link": "", "article_chapter_link": "", "book_review_link": "", "first_chapter_link": ""}]}, {"list_name": "Picture Books", "asterisk": 0, "published_date": "2017-03-12", "book_details": [{"primary_isbn13": "9781419721373", "contributor_note": "Illustrated by David Roberts", "primary_isbn10": "1419721372", "description": "A girl emerges with a love of science.", "contributor": "by Andrea Beaty. Illustrated by David Roberts", "publisher": "Abrams", "title": "ADA TWIST, SCIENTIST", "author": "Andrea Beaty", "age_group": "", "price": 0}], "weeks_on_list": 25, "bestsellers_date": "2017-02-25", "rank": 4, "display_name": "Children\u2019s Picture Books", "dagger": 0, "amazon_product_url": "http://www.amazon.com/Ada-Twist-Scientist-Andrea-Beaty/dp/1419721372?tag=thenewyorktim-20", "isbns": [{"isbn10": "1419721372", "isbn13": "9781419721373"}], "rank_last_week": 6, "reviews": [{"sunday_review_link": "", "article_chapter_link": "", "book_review_link": "", "first_chapter_link": ""}]}, {"list_name": "Picture Books", "asterisk": 0, "published_date": "2017-03-12", "book_details": [{"primary_isbn13": "9780399255373", "contributor_note": "Illustrated by Oliver Jeffers", "primary_isbn10": "0399255370", "description": "Problems arise when Duncan\u2019s crayons revolt.", "contributor": "by Drew Daywalt. Illustrated by Oliver Jeffers", "publisher": "Philomel", "title": "THE DAY THE CRAYONS QUIT", "author": "Drew Daywalt", "age_group": "", "price": 0}], "weeks_on_list": 192, "bestsellers_date": "2017-02-25", "rank": 5, "display_name": "Children\u2019s Picture Books", "dagger": 0, "amazon_product_url": "http://www.amazon.com/The-Crayons-Quit-Drew-Daywalt/dp/0399255370?tag=thenewyorktim-20", "isbns": [{"isbn10": "0399255370", "isbn13": "9780399255373"}], "rank_last_week": 9, "reviews": [{"sunday_review_link": "https://www.nytimes.com/2013/08/25/books/review/henris-scissors-by-jeanette-winter-and-more.html", "article_chapter_link": "", "book_review_link": "", "first_chapter_link": ""}]}, {"list_name": "Picture Books", "asterisk": 0, "published_date": "2017-03-12", "book_details": [{"primary_isbn13": "9780385376716", "contributor_note": "", "primary_isbn10": "0385376715", "description": "A celebration of future possibilities.", "contributor": "by Emily Winfield Martin", "publisher": "Random House", "title": "THE WONDERFUL THINGS YOU WILL BE", "author": "Emily Winfield Martin", "age_group": "", "price": 0}], "weeks_on_list": 74, "bestsellers_date": "2017-02-25", "rank": 6, "display_name": "Children\u2019s Picture Books", "dagger": 0, "amazon_product_url": "http://www.amazon.com/The-Wonderful-Things-You-Will/dp/0385376715?tag=thenewyorktim-20", "isbns": [{"isbn10": "0385376715", "isbn13": "9780385376716"}], "rank_last_week": 8, "reviews": [{"sunday_review_link": "", "article_chapter_link": "", "book_review_link": "", "first_chapter_link": ""}]}, {"list_name": "Picture Books", "asterisk": 0, "published_date": "2017-03-12", "book_details": [{"primary_isbn13": "9780803741713", "contributor_note": "", "primary_isbn10": "0803741715", "description": "Silly songs and sound effects.", "contributor": "by B. J. Novak", "publisher": "Dial", "title": "THE BOOK WITH NO PICTURES", "author": "B J Novak", "age_group": "", "price": 0}], "weeks_on_list": 125, "bestsellers_date": "2017-02-25", "rank": 7, "display_name": "Children\u2019s Picture Books", "dagger": 0, "amazon_product_url": "http://www.amazon.com/The-Book-Pictures-B-J-Novak/dp/0803741715?tag=thenewyorktim-20", "isbns": [{"isbn10": "0803741715", "isbn13": "9780803741713"}], "rank_last_week": 7, "reviews": [{"sunday_review_link": "https://www.nytimes.com/2014/11/09/books/review/b-j-novaks-book-with-no-pictures-and-more.html", "article_chapter_link": "", "book_review_link": "", "first_chapter_link": ""}]}, {"list_name": "Picture Books", "asterisk": 0, "published_date": "2017-03-12", "book_details": [{"primary_isbn13": "9781419708459", "contributor_note": "Illustrated by David Roberts", "primary_isbn10": "1419708457", "description": "A young inventor learns to fail better.", "contributor": "by Andrea Beaty. Illustrated by David Roberts", "publisher": "Abrams", "title": "ROSIE REVERE, ENGINEER", "author": "Andrea Beaty", "age_group": "", "price": 0}], "weeks_on_list": 89, "bestsellers_date": "2017-02-25", "rank": 8, "display_name": "Children\u2019s Picture Books", "dagger": 0, "amazon_product_url": "http://www.amazon.com/Rosie-Revere-Engineer-Andrea-Beaty/dp/1419708457?tag=thenewyorktim-20", "isbns": [{"isbn10": "1419708457", "isbn13": "9781419708459"}], "rank_last_week": 10, "reviews": [{"sunday_review_link": "", "article_chapter_link": "", "book_review_link": "", "first_chapter_link": ""}]}, {"list_name": "Picture Books", "asterisk": 0, "published_date": "2017-03-12", "book_details": [{"primary_isbn13": "9781423199571", "contributor_note": "", "primary_isbn10": "142319957X", "description": "Impatient Gerald has to wait for Piggie\u2019s promised surprise.", "contributor": "by Mo Willems", "publisher": "Hyperion", "title": "WAITING IS NOT EASY!", "author": "Mo Willems", "age_group": "", "price": 0}], "weeks_on_list": 46, "bestsellers_date": "2017-02-25", "rank": 9, "display_name": "Children\u2019s Picture Books", "dagger": 0, "amazon_product_url": "http://www.amazon.com/Waiting-Easy-Elephant-Piggie-Book/dp/142319957X?tag=thenewyorktim-20", "isbns": [{"isbn10": "142319957X", "isbn13": "9781423199571"}], "rank_last_week": 0, "reviews": [{"sunday_review_link": "", "article_chapter_link": "", "book_review_link": "", "first_chapter_link": ""}]}, {"list_name": "Picture Books", "asterisk": 0, "published_date": "2017-03-12", "book_details": [{"primary_isbn13": "9781481465595", "contributor_note": "Illustrated by Elizabeth Baddeley", "primary_isbn10": "1481465597", "description": "A groundbreaking jurist, Ruth Bader Ginsburg, scales the legal ladder.", "contributor": "by Debbie Levy. Illustrated by Elizabeth Baddeley", "publisher": "Simon & Schuster", "title": "I DISSENT", "author": "Debbie Levy", "age_group": "", "price": 0}], "weeks_on_list": 4, "bestsellers_date": "2017-02-25", "rank": 10, "display_name": "Children\u2019s Picture Books", "dagger": 0, "amazon_product_url": "https://www.amazon.com/Dissent-Ruth-Bader-Ginsburg-Makes/dp/1481465597?tag=thenewyorktim-20", "isbns": [{"isbn10": "1481465597", "isbn13": "9781481465595"}], "rank_last_week": 0, "reviews": [{"sunday_review_link": "", "article_chapter_link": "", "book_review_link": "", "first_chapter_link": ""}]}]