{"blog": [], "source": "Reuters", "document_type": "article", "word_count": "366", "lead_paragraph": "It was not quite the triple bagel that Novak Djokovic was aiming for during the opening 41 minutes of his first-round match but the Serbian is unlikely to be too disappointed after he beat Britain's James Ward 6-0 7-6(3) 6-4 at Wimbledon on Monday.", "web_url": "http://www.nytimes.com/reuters/2016/06/27/sports/tennis/27reuters-tennis-wimbledon-djokovic.html", "print_page": null, "section_name": "Sports", "abstract": null, "keywords": [], "_id": "5771394838f0d81704054a8f", "snippet": "It was not quite the triple bagel that Novak Djokovic was aiming for during the opening 41 minutes of his first-round match but the Serbian is unlikely to be too disappointed after he beat Britain's James Ward 6-0 7-6(3) 6-4 at Wimbledon on Monday...", "news_desk": "None", "slideshow_credits": null, "byline": {"organization": "REUTERS", "person": [], "original": "By REUTERS"}, "multimedia": [], "headline": {"main": "Djokovic Makes Solid Start to Wimbledon Title Defence", "print_headline": "Djokovic Makes Solid Start to Wimbledon Title Defence"}, "type_of_material": "News", "pub_date": "2016-06-27T10:29:21Z", "subsection_name": "Tennis"}