{"blog": [], "source": "The New York Times", "document_type": "article", "word_count": "431", "lead_paragraph": "The top-ranked Murray, who outlasted Milos Raonic, and Djokovic, who cruised past Kei Nishikori, will meet Sunday in London.", "web_url": "http://www.nytimes.com/2016/11/20/sports/tennis/andy-murray-and-novak-djokovic-aim-for-atp-title-and-no-1.html", "print_page": "10", "section_name": "Sports", "abstract": null, "keywords": [{"value": "Tennis", "is_major": "N", "rank": "1", "name": "subject"}, {"value": "Djokovic, Novak", "is_major": "N", "rank": "2", "name": "persons"}, {"value": "Murray, Andy (1987- )", "is_major": "N", "rank": "3", "name": "persons"}, {"value": "Assn of Tennis Professionals", "is_major": "N", "rank": "4", "name": "organizations"}, {"value": "London (England)", "is_major": "N", "rank": "5", "name": "glocations"}], "_id": "5830fb9395d0e0392607187e", "snippet": "The top-ranked Murray, who outlasted Milos Raonic, and Djokovic, who cruised past Kei Nishikori, will meet Sunday in London....", "news_desk": "Sports", "slideshow_credits": null, "byline": {"organization": "THE ASSOCIATED PRESS", "person": [], "contributor": "", "original": "By THE ASSOCIATED PRESS"}, "multimedia": [{"subtype": "wide", "height": 126, "type": "image", "url": "images/2016/11/20/sports/20TENNIS2/20TENNIS2-thumbWide.jpg", "width": 190, "legacy": {"widewidth": "190", "wideheight": "126", "wide": "images/2016/11/20/sports/20TENNIS2/20TENNIS2-thumbWide.jpg"}}, {"subtype": "xlarge", "height": 390, "type": "image", "url": "images/2016/11/20/sports/20TENNIS2/20TENNIS2-articleLarge.jpg", "width": 600, "legacy": {"xlargeheight": "390", "xlarge": "images/2016/11/20/sports/20TENNIS2/20TENNIS2-articleLarge.jpg", "xlargewidth": "600"}}, {"subtype": "thumbnail", "height": 75, "type": "image", "url": "images/2016/11/20/sports/20TENNIS2/20TENNIS2-thumbStandard.jpg", "width": 75, "legacy": {"thumbnailheight": "75", "thumbnail": "images/2016/11/20/sports/20TENNIS2/20TENNIS2-thumbStandard.jpg", "thumbnailwidth": "75"}}], "headline": {"main": "Andy Murray and Novak Djokovic Aim for ATP Title and No. 1", "print_headline": "Murray and Djokovic Aim for Dual Prize"}, "type_of_material": "News", "pub_date": "2016-11-20T01:25:34+0000", "subsection_name": "Tennis"}