{"news_desk": "None", "abstract": null, "source": "", "lead_paragraph": "They teamed up for a carpool karaoke video. They planted their flag in Brazil. And when the Olympics are done, they'll be remembered as the latest in a long line of U.S. swimming powerhouses.", "word_count": "853", "multimedia": [], "blog": [], "headline": {"main": "So Much for the Dire Predictions of US Swimming Flop in Rio", "print_headline": "So Much for the Dire Predictions of US Swimming Flop in Rio"}, "print_page": null, "pub_date": "2016-08-13T22:32:41Z", "document_type": "article", "byline": {"organization": "THE ASSOCIATED PRESS", "original": "By THE ASSOCIATED PRESS", "person": []}, "_id": "57afa11395d0e021d79808e7", "slideshow_credits": null, "type_of_material": "News", "subsection_name": "Olympics", "section_name": "Sports", "snippet": "They teamed up for a carpool karaoke video. They planted their flag in Brazil. And when the Olympics are done, they'll be remembered as the latest in a long line of U.S. swimming powerhouses....", "web_url": "http://www.nytimes.com/aponline/2016/08/13/sports/olympics/ap-oly-swm-dominant-americans.html", "keywords": []}