{"news_desk": "None", "abstract": null, "source": "AP", "lead_paragraph": "Katie Ledecky was barely in the pool when American swim great Michael Phelps was asked about the precocious teenager who seems to mow down world records at will.", "word_count": "644", "multimedia": [], "blog": [], "headline": {"main": "Ledecky Breaks Own World Record in Women's 800 Freestyle", "print_headline": "Ledecky Breaks Own World Record in Women's 800 Freestyle"}, "print_page": null, "pub_date": "2016-01-17T20:44:58Z", "document_type": "article", "byline": {"organization": "THE ASSOCIATED PRESS", "original": "By THE ASSOCIATED PRESS", "person": []}, "_id": "569c43cb38f0d821e003cdc2", "slideshow_credits": null, "type_of_material": "News", "subsection_name": null, "section_name": "Sports", "snippet": "Katie Ledecky was barely in the pool when American swim great Michael Phelps was asked about the precocious teenager who seems to mow down world records at will....", "web_url": "http://www.nytimes.com/aponline/2016/01/17/sports/ap-swm-austin-pro-series.html", "keywords": []}