{"news_desk": null, "abstract": null, "source": "AP", "lead_paragraph": "Although LeBron James is getting Sports Illustrated's Sportsperson of the Year award, Michael Phelps' phenomenal year won't go unrecognized at an event next week that will celebrate both athletes.", "word_count": "134", "multimedia": [], "blog": [], "headline": {"main": "Phelps to Get Special Honor From SI at Ceremony", "print_headline": "Phelps to Get Special Honor From SI at Ceremony"}, "print_page": null, "pub_date": "2016-12-07T20:04:57+0000", "document_type": "article", "byline": {"organization": "THE ASSOCIATED PRESS", "original": "By THE ASSOCIATED PRESS", "person": []}, "_id": "58486b7295d0e03926074b30", "slideshow_credits": null, "type_of_material": "News", "subsection_name": null, "section_name": "Arts", "snippet": "Although LeBron James is getting Sports Illustrated's Sportsperson of the Year award, Michael Phelps' phenomenal year won't go unrecognized at an event next week that will celebrate both athletes....", "web_url": "http://www.nytimes.com/aponline/2016/12/07/arts/ap-us-people-michael-phelps.html", "keywords": []}