{"news_desk": "None", "abstract": null, "source": "", "lead_paragraph": "Michael Phelps won two gold medals on Tuesday, avenging his 200 meters butterfly defeat from the London Olympics and then anchoring the U.S. 4x200 freestyle team to victory on a night of high drama and emotion in the pool.", "word_count": "621", "multimedia": [], "blog": [], "headline": {"main": "Two More Golds for Phelps, Hosszu and Ledecky March On", "print_headline": "Two More Golds for Phelps, Hosszu and Ledecky March On"}, "print_page": null, "pub_date": "2016-08-10T05:16:50Z", "document_type": "article", "byline": {"organization": "REUTERS", "original": "By REUTERS", "person": []}, "_id": "57aab92c95d0e021d797fd56", "slideshow_credits": null, "type_of_material": "News", "subsection_name": "Olympics", "section_name": "Sports", "snippet": "Michael Phelps won two gold medals on Tuesday, avenging his 200 meters butterfly defeat from the London Olympics and then anchoring the U.S. 4x200 freestyle team to victory on a night of high drama and emotion in the pool....", "web_url": "http://www.nytimes.com/reuters/2016/08/10/sports/olympics/10reuters-olympics-rio-swimming-wrapup.html", "keywords": []}